async_mixin/__init__.py
async_mixin/mixin.py
async_mixin-0.0.3.dist-info/LICENSE
async_mixin-0.0.3.dist-info/WHEEL
async_mixin-0.0.3.dist-info/METADATA
async_mixin-0.0.3.dist-info/RECORD
